emoji_gg/emoji.py
emoji_gg/errors.py
emoji_gg/stats.py
emoji.gg_tako-0.0.10.dist-info/LICENSE
emoji.gg_tako-0.0.10.dist-info/METADATA
emoji.gg_tako-0.0.10.dist-info/WHEEL
emoji.gg_tako-0.0.10.dist-info/top_level.txt
emoji.gg_tako-0.0.10.dist-info/RECORD
