Metadata-Version: 2.1
Name: emoji.gg-tako
Version: 0.0.10
Summary: (Unofficial) API Wrapper for emoji.gg
Home-page: https://github.com/kayano-bot/EmojiGG-Wrapper
Author: Pukima
Author-email: pukima@pukima.site
License: MIT
Project-URL: Source Code, https://github.com/kayano-bot/EmojiGG-Wrapper
Project-URL: Discord, https://discord.gg/dfmXNTmzyp
Project-URL: Issue tracker, https://github.com/kayano-bot/EmojiGG-Wrapper/issues
Keywords: python,emojigg,apiwrapper
Platform: UNKNOWN
Classifier: Development Status :: 3 - Alpha
Classifier: Intended Audience :: Developers
Classifier: Topic :: Software Development :: Build Tools
Classifier: License :: OSI Approved :: MIT License
Classifier: Programming Language :: Python :: 3
License-File: LICENSE
Requires-Dist: aiohttp
